dedev/__init__.py
dedev/__main__.py
sudocode-0.0.1.dist-info/LICENSE.txt
sudocode-0.0.1.dist-info/METADATA
sudocode-0.0.1.dist-info/WHEEL
sudocode-0.0.1.dist-info/entry_points.txt
sudocode-0.0.1.dist-info/top_level.txt
sudocode-0.0.1.dist-info/RECORD
