Metadata-Version: 2.1
Name: sudocode
Version: 0.0.1
Summary: A simple Python library
Author-email: Randy Song <ssh.randy@sudocode.ai>, Alex Ngai <alex@sudocode.ai>, Ning Ren <ning@gmail.com>
Maintainer-email: Randy Song <ssh.randy@sudocode.ai>, Alex Ngai <alex@sudocode.ai>, Ning Ren <ning@gmail.com>
Project-URL: Homepage, https://github.com/sudocode-ai/py-sudocode
Project-URL: Bug Reports, https://github.com/sudocode-ai/py-sudocode/issues
Project-URL: Funding, https://github.com/sudocode-ai/py-sudocode
Project-URL: Say Thanks!, https://github.com/sudocode-ai/py-sudocode
Project-URL: Source, https://github.com/sudocode-ai/py-sudocode
Keywords: setuptools,development
Classifier: Development Status :: 3 - Alpha
Classifier: Intended Audience :: Developers
Classifier: Topic :: Software Development :: Build Tools
Classifier: License :: OSI Approved :: MIT License
Classifier: Programming Language :: Python :: 3
Classifier: Programming Language :: Python :: 3.7
Classifier: Programming Language :: Python :: 3.8
Classifier: Programming Language :: Python :: 3.9
Classifier: Programming Language :: Python :: 3.10
Classifier: Programming Language :: Python :: 3.11
Classifier: Programming Language :: Python :: 3 :: Only
Requires-Python: >=3.7
License-File: LICENSE.txt
Requires-Dist: ray[default] ==2.11.0
Provides-Extra: dev
Requires-Dist: check-manifest ; extra == 'dev'
Provides-Extra: test
Requires-Dist: coverage ; extra == 'test'
